{"nodes": [{"id": "testdata_eso_client_ca_eso_client_ca", "label": "eso-client-ca ConfigMap (remote serving-CA bundle)", "file_type": "code", "source_file": "tools/testdata/eso-client-ca.yaml", "source_location": null, "source_url": null, "captured_at": null, "author": null, "contributor": null}, {"id": "policy_eso_server_ca_trust", "label": "policy-external-secrets-operator-server-ca-trust", "file_type": "concept", "source_file": "tools/testdata/eso-client-ca.yaml", "source_location": null, "source_url": null, "captured_at": null, "author": null, "contributor": null}], "edges": [{"source": "policy_eso_server_ca_trust", "target": "testdata_eso_client_ca_eso_client_ca", "relation": "references", "confidence": "EXTRACTED", "confidence_score": 1.0, "source_file": "tools/testdata/eso-client-ca.yaml", "source_location": null, "weight": 1.0}, {"source": "testdata_eso_client_ca_eso_client_ca", "target": "testdata_eso_hub_bootstrap_hub_ca_cm", "relation": "semantically_similar_to", "confidence": "INFERRED", "confidence_score": 0.7, "source_file": "tools/testdata/eso-client-ca.yaml", "source_location": null, "weight": 1.0}], "hyperedges": []}