{"nodes": [{"id": "images_acm_confirm_changes_screen", "label": "ACM Confirm Changes Dialog", "file_type": "image", "source_file": "images/acm-confirm-changes.png", "source_location": null, "source_url": null, "captured_at": null, "author": null, "contributor": null}, {"id": "images_acm_confirm_changes_manage_resource_assignments", "label": "Manage Resource Assignments Page", "file_type": "image", "source_file": "images/acm-confirm-changes.png", "source_location": null, "source_url": null, "captured_at": null, "author": null, "contributor": null}, {"id": "images_acm_confirm_changes_cluster_set_hub", "label": "Cluster Set hub", "file_type": "image", "source_file": "images/acm-confirm-changes.png", "source_location": null, "source_url": null, "captured_at": null, "author": null, "contributor": null}, {"id": "images_acm_confirm_changes_local_cluster", "label": "local-cluster", "file_type": "image", "source_file": "images/acm-confirm-changes.png", "source_location": null, "source_url": null, "captured_at": null, "author": null, "contributor": null}, {"id": "images_acm_confirm_changes_default_cluster_set", "label": "default Cluster Set", "file_type": "image", "source_file": "images/acm-confirm-changes.png", "source_location": null, "source_url": null, "captured_at": null, "author": null, "contributor": null}, {"id": "images_acm_confirm_changes_transferred_change", "label": "Transferred Change", "file_type": "image", "source_file": "images/acm-confirm-changes.png", "source_location": null, "source_url": null, "captured_at": null, "author": null, "contributor": null}, {"id": "images_acm_confirm_changes_red_hat_openshift_acm", "label": "Red Hat OpenShift ACM Console", "file_type": "image", "source_file": "images/acm-confirm-changes.png", "source_location": null, "source_url": null, "captured_at": null, "author": null, "contributor": null}], "edges": [{"source": "images_acm_confirm_changes_screen", "target": "images_acm_confirm_changes_manage_resource_assignments", "relation": "references", "confidence": "EXTRACTED", "confidence_score": 1.0, "source_file": "images/acm-confirm-changes.png", "source_location": null, "weight": 1.0}, {"source": "images_acm_confirm_changes_manage_resource_assignments", "target": "images_acm_confirm_changes_cluster_set_hub", "relation": "references", "confidence": "EXTRACTED", "confidence_score": 1.0, "source_file": "images/acm-confirm-changes.png", "source_location": null, "weight": 1.0}, {"source": "images_acm_confirm_changes_screen", "target": "images_acm_confirm_changes_local_cluster", "relation": "references", "confidence": "EXTRACTED", "confidence_score": 1.0, "source_file": "images/acm-confirm-changes.png", "source_location": null, "weight": 1.0}, {"source": "images_acm_confirm_changes_local_cluster", "target": "images_acm_confirm_changes_default_cluster_set", "relation": "conceptually_related_to", "confidence": "EXTRACTED", "confidence_score": 1.0, "source_file": "images/acm-confirm-changes.png", "source_location": null, "weight": 1.0}, {"source": "images_acm_confirm_changes_local_cluster", "target": "images_acm_confirm_changes_transferred_change", "relation": "references", "confidence": "EXTRACTED", "confidence_score": 1.0, "source_file": "images/acm-confirm-changes.png", "source_location": null, "weight": 1.0}, {"source": "images_acm_confirm_changes_transferred_change", "target": "images_acm_confirm_changes_cluster_set_hub", "relation": "conceptually_related_to", "confidence": "INFERRED", "confidence_score": 0.85, "source_file": "images/acm-confirm-changes.png", "source_location": null, "weight": 1.0}, {"source": "images_acm_confirm_changes_manage_resource_assignments", "target": "images_acm_confirm_changes_red_hat_openshift_acm", "relation": "conceptually_related_to", "confidence": "EXTRACTED", "confidence_score": 1.0, "source_file": "images/acm-confirm-changes.png", "source_location": null, "weight": 1.0}], "hyperedges": []}