{"nodes": [{"id": "cluster_labels_chart", "label": "cluster-labels Chart", "file_type": "code", "source_file": "policies/stable/cluster-labels/Chart.yaml", "source_location": null, "source_url": null, "captured_at": null, "author": null, "contributor": null}], "edges": [{"source": "cluster_labels_chart", "target": "cluster_labels_policy_cluster_labels", "relation": "conceptually_related_to", "confidence": "INFERRED", "confidence_score": 0.75, "source_file": "policies/stable/cluster-labels/Chart.yaml", "source_location": null, "weight": 1.0}], "hyperedges": []}